hasnaink/__init__.py
hasnaink/client.py
hasnaink/dispatcher.py
hasnaink/emoji.py
hasnaink/file_id.py
hasnaink/filters.py
hasnaink/mime_types.py
hasnaink/py.typed
hasnaink/sync.py
hasnaink/utils.py
hasnaink/connection/__init__.py
hasnaink/connection/connection.py
hasnaink/connection/transport/__init__.py
hasnaink/connection/transport/tcp/__init__.py
hasnaink/connection/transport/tcp/tcp.py
hasnaink/connection/transport/tcp/tcp_abridged.py
hasnaink/connection/transport/tcp/tcp_abridged_o.py
hasnaink/connection/transport/tcp/tcp_full.py
hasnaink/connection/transport/tcp/tcp_intermediate.py
hasnaink/connection/transport/tcp/tcp_intermediate_o.py
hasnaink/crypto/__init__.py
hasnaink/crypto/aes.py
hasnaink/crypto/mtproto.py
hasnaink/crypto/prime.py
hasnaink/crypto/rsa.py
hasnaink/enums/__init__.py
hasnaink/enums/auto_name.py
hasnaink/enums/chat_action.py
hasnaink/enums/chat_event_action.py
hasnaink/enums/chat_member_status.py
hasnaink/enums/chat_members_filter.py
hasnaink/enums/chat_type.py
hasnaink/enums/message_entity_type.py
hasnaink/enums/message_media_type.py
hasnaink/enums/message_service_type.py
hasnaink/enums/messages_filter.py
hasnaink/enums/next_code_type.py
hasnaink/enums/parse_mode.py
hasnaink/enums/poll_type.py
hasnaink/enums/sent_code_type.py
hasnaink/enums/user_status.py
hasnaink/errors/__init__.py
hasnaink/errors/rpc_error.py
hasnaink/handlers/__init__.py
hasnaink/handlers/callback_query_handler.py
hasnaink/handlers/chat_join_request_handler.py
hasnaink/handlers/chat_member_updated_handler.py
hasnaink/handlers/chosen_inline_result_handler.py
hasnaink/handlers/deleted_messages_handler.py
hasnaink/handlers/disconnect_handler.py
hasnaink/handlers/edited_message_handler.py
hasnaink/handlers/handler.py
hasnaink/handlers/inline_query_handler.py
hasnaink/handlers/message_handler.py
hasnaink/handlers/poll_handler.py
hasnaink/handlers/raw_update_handler.py
hasnaink/handlers/user_status_handler.py
hasnaink/methods/__init__.py
hasnaink/methods/advanced/__init__.py
hasnaink-3.0.dist-info/COPYING
hasnaink-3.0.dist-info/COPYING.lesser
hasnaink-3.0.dist-info/METADATA
hasnaink-3.0.dist-info/NOTICE
hasnaink-3.0.dist-info/WHEEL
hasnaink-3.0.dist-info/top_level.txt
hasnaink-3.0.dist-info/RECORD
